cka_pytorch/__init__.py
cka_pytorch/cka.py
cka_pytorch/hook_manager.py
cka_pytorch/hsic.py
cka_pytorch/metrics.py
cka_pytorch/plot.py
cka_pytorch/utils.py
cka_pytorch-1.1.3.dist-info/licenses/LICENSE
cka_pytorch-1.1.3.dist-info/METADATA
cka_pytorch-1.1.3.dist-info/WHEEL
cka_pytorch-1.1.3.dist-info/top_level.txt
cka_pytorch-1.1.3.dist-info/RECORD
