Metadata-Version: 2.4
Name: cka-pytorch
Version: 1.1.3
Summary: A PyTorch implementation of Centered Kernel Alignment (CKA) with GPU support.
Author-email: Dat-Thinh Nguyen <datthinh1801@gmail.com>
Project-URL: Homepage, https://github.com/datthinh1801/CKA.pytorch
Project-URL: Repository, https://github.com/datthinh1801/CKA.pytorch.git
Project-URL: Issues, https://github.com/datthinh1801/CKA.pytorch/issues
Keywords: pytorch,cka,centered kernel alignment
Classifier: Programming Language :: Python :: 3
Classifier: Operating System :: OS Independent
Requires-Python: >=3.11
License-File: LICENSE
Requires-Dist: lightning
Requires-Dist: matplotlib
Requires-Dist: seaborn
Requires-Dist: torch
Requires-Dist: torchmetrics
Requires-Dist: torchvision
Requires-Dist: tqdm
Dynamic: license-file
